cocotbext/uart/__init__.py
cocotbext/uart/uart.py
cocotbext/uart/version.py
cocotbext_uart-0.1.4.dist-info/licenses/LICENSE
cocotbext_uart-0.1.4.dist-info/METADATA
cocotbext_uart-0.1.4.dist-info/WHEEL
cocotbext_uart-0.1.4.dist-info/top_level.txt
cocotbext_uart-0.1.4.dist-info/RECORD
